ProgramizCJiaochengChuyi/README.md
ProgramizCJiaochengChuyi/__init__.py
ProgramizCJiaochengChuyi/__main__.py
ProgramizCJiaochengChuyi/file.epub
ProgramizCJiaochengChuyi/index.html
ProgramizCJiaochengChuyi/css/__init__.py
ProgramizCJiaochengChuyi/css/annotations.css
ProgramizCJiaochengChuyi/css/main.css
ProgramizCJiaochengChuyi/css/normalize.css
ProgramizCJiaochengChuyi/css/popup.css
ProgramizCJiaochengChuyi/font/__init__.py
ProgramizCJiaochengChuyi/font/fontello.eot
ProgramizCJiaochengChuyi/font/fontello.svg
ProgramizCJiaochengChuyi/font/fontello.ttf
ProgramizCJiaochengChuyi/font/fontello.woff
ProgramizCJiaochengChuyi/img/__init__.py
ProgramizCJiaochengChuyi/img/annotator-glyph-sprite.png
ProgramizCJiaochengChuyi/img/annotator-icon-sprite.png
ProgramizCJiaochengChuyi/img/apple-touch-icon.png
ProgramizCJiaochengChuyi/img/cancelfullscreen.png
ProgramizCJiaochengChuyi/img/close.png
ProgramizCJiaochengChuyi/img/fullscreen.png
ProgramizCJiaochengChuyi/img/loader.gif
ProgramizCJiaochengChuyi/img/menu-icon.png
ProgramizCJiaochengChuyi/img/save.png
ProgramizCJiaochengChuyi/img/saved.png
ProgramizCJiaochengChuyi/img/settings-s.png
ProgramizCJiaochengChuyi/img/settings.png
ProgramizCJiaochengChuyi/img/star.png
ProgramizCJiaochengChuyi/js/__init__.py
ProgramizCJiaochengChuyi/js/epub.js
ProgramizCJiaochengChuyi/js/epub.min.js
ProgramizCJiaochengChuyi/js/epub.min.map
ProgramizCJiaochengChuyi/js/hooks.min.js
ProgramizCJiaochengChuyi/js/hooks.min.map
ProgramizCJiaochengChuyi/js/reader.js
ProgramizCJiaochengChuyi/js/reader.js.map
ProgramizCJiaochengChuyi/js/reader.min.js
ProgramizCJiaochengChuyi/js/reader.min.map
ProgramizCJiaochengChuyi/js/hooks/__init__.py
ProgramizCJiaochengChuyi/js/hooks/extensions/__init__.py
ProgramizCJiaochengChuyi/js/hooks/extensions/highlight.js
ProgramizCJiaochengChuyi/js/libs/__init__.py
ProgramizCJiaochengChuyi/js/libs/jquery.min.js
ProgramizCJiaochengChuyi/js/libs/localforage.min.js
ProgramizCJiaochengChuyi/js/libs/screenfull.js
programiz_c_jiaocheng_chuyi-2024.3.5.0.dist-info/METADATA
programiz_c_jiaocheng_chuyi-2024.3.5.0.dist-info/WHEEL
programiz_c_jiaocheng_chuyi-2024.3.5.0.dist-info/entry_points.txt
programiz_c_jiaocheng_chuyi-2024.3.5.0.dist-info/top_level.txt
programiz_c_jiaocheng_chuyi-2024.3.5.0.dist-info/RECORD
